{
  "totalTrades": 42,
  "wins": 17,
  "losses": 25,
  "longTrades": 24,
  "longWins": 11,
  "shortTrades": 18,
  "shortWins": 6,
  "cancelledTrades": 0,
  "totalPnL": -130.10329272774035,
  "finalBalance": 4869.896707272258,
  "totalFees": 1182.9481769884533,
  "totalSlippage": 473.1792707953813,
  "isLiquidated": false,
  "liquidationDate": null,
  "trades": [
    {
      "time": "2020-01-01T12:43:00.000Z",
      "type": "LONG",
      "entryPrice": 7219,
      "exitPrice": 7209.107571428572,
      "status": "LOSS",
      "pnlR": -1,
      "dollarPnL": -50,
      "estimatedFee": 36.48750126359345,
      "estimatedSlippage": 14.59500050543738,
      "currentBalance": 4950,
      "reason": "TA Entry",
      "regime": "HIGH_WINRATE",
      "efficiency": "EXPANSION",
      "effValue": null,
      "riskPercent": 1
    },
    {
      "time": "2020-01-01T19:55:00.000Z",
      "type": "SHORT",
      "entryPrice": 7225.01,
      "exitPrice": 7228.193214285714,
      "status": "LOSS",
      "pnlR": -1,
      "dollarPnL": -49.5,
      "estimatedFee": 112.35121575228902,
      "estimatedSlippage": 44.94048630091561,
      "currentBalance": 4900.5,
      "reason": "TA Entry",
      "regime": "HIGH_WINRATE",
      "efficiency": "EXPANSION",
      "effValue": null,
      "riskPercent": 1
    },
    {
      "time": "2020-01-02T10:10:00.000Z",
      "type": "LONG",
      "entryPrice": 7165.89,
      "exitPrice": 7158.54,
      "status": "LOSS",
      "pnlR": -1,
      "dollarPnL": -49.005,
      "estimatedFee": 47.77747475509968,
      "estimatedSlippage": 19.110989902039876,
      "currentBalance": 4851.495,
      "reason": "TA Entry",
      "regime": "HIGH_WINRATE",
      "efficiency": "EXPANSION",
      "effValue": null,
      "riskPercent": 1
    },
    {
      "time": "2020-01-02T11:52:00.000Z",
      "type": "SHORT",
      "entryPrice": 7145.02,
      "exitPrice": 7140.481428571428,
      "status": "WIN",
      "pnlR": 1.2000000000000481,
      "dollarPnL": 58.217940000002336,
      "estimatedFee": 91.65182309132074,
      "estimatedSlippage": 36.6607292365283,
      "currentBalance": 4909.712940000002,
      "reason": "TA Entry",
      "regime": "HIGH_WINRATE",
      "efficiency": "EXPANSION",
      "effValue": null,
      "riskPercent": 1
    },
    {
      "time": "2020-01-02T16:39:00.000Z",
      "type": "SHORT",
      "entryPrice": 7115.16,
      "exitPrice": 7108.344428571429,
      "status": "WIN",
      "pnlR": 1.2000000000000641,
      "dollarPnL": 58.91655528000317,
      "estimatedFee": 61.50632002897856,
      "estimatedSlippage": 24.60252801159142,
      "currentBalance": 4968.629495280005,
      "reason": "TA Entry",
      "regime": "HIGH_WINRATE",
      "efficiency": "EXPANSION",
      "effValue": null,
      "riskPercent": 1
    },
    {
      "time": "2020-01-02T18:15:00.000Z",
      "type": "SHORT",
      "entryPrice": 6955.45,
      "exitPrice": 6963.966785714286,
      "status": "LOSS",
      "pnlR": -1,
      "dollarPnL": -49.686294952800054,
      "estimatedFee": 40.577578422545166,
      "estimatedSlippage": 16.231031369018066,
      "currentBalance": 4918.943200327205,
      "reason": "TA Entry",
      "regime": "HIGH_WINRATE",
      "efficiency": "EXPANSION",
      "effValue": null,
      "riskPercent": 1
    },
    {
      "time": "2020-01-04T10:47:00.000Z",
      "type": "SHORT",
      "entryPrice": 7342.01,
      "exitPrice": 7347.778571428572,
      "status": "LOSS",
      "pnlR": -1,
      "dollarPnL": -49.18943200327205,
      "estimatedFee": 62.606367301542434,
      "estimatedSlippage": 25.042546920616974,
      "currentBalance": 4869.7537683239325,
      "reason": "TA Entry",
      "regime": "HIGH_WINRATE",
      "efficiency": "EXPANSION",
      "effValue": null,
      "riskPercent": 1
    },
    {
      "time": "2020-01-04T11:47:00.000Z",
      "type": "LONG",
      "entryPrice": 7333.83,
      "exitPrice": 7327.570285714286,
      "status": "LOSS",
      "pnlR": -1,
      "dollarPnL": -48.697537683239325,
      "estimatedFee": 57.0536363940034,
      "estimatedSlippage": 22.82145455760136,
      "currentBalance": 4821.056230640693,
      "reason": "TA Entry",
      "regime": "HIGH_WINRATE",
      "efficiency": "EXPANSION",
      "effValue": null,
      "riskPercent": 1
    },
    {
      "time": "2020-01-05T08:45:00.000Z",
      "type": "SHORT",
      "entryPrice": 7444.95,
      "exitPrice": 7436.898514285714,
      "status": "WIN",
      "pnlR": 1.2000000000000541,
      "dollarPnL": 28.92633738384546,
      "estimatedFee": 26.74725425193817,
      "estimatedSlippage": 10.698901700775268,
      "currentBalance": 4849.9825680245385,
      "reason": "TA Entry",
      "regime": "NEUTRAL",
      "efficiency": "NEUTRAL",
      "effValue": null,
      "riskPercent": 0.5
    },
    {
      "time": "2020-01-05T11:19:00.000Z",
      "type": "LONG",
      "entryPrice": 7423.33,
      "exitPrice": 7433.896514285714,
      "status": "WIN",
      "pnlR": 1.1999999999999587,
      "dollarPnL": 14.549947704073114,
      "estimatedFee": 10.221825321913757,
      "estimatedSlippage": 4.088730128765503,
      "currentBalance": 4864.5325157286115,
      "reason": "TA Entry",
      "regime": "LOW_WINRATE",
      "efficiency": "CHOPPY",
      "effValue": null,
      "riskPercent": 0.25
    },
    {
      "time": "2020-01-07T10:48:00.000Z",
      "type": "LONG",
      "entryPrice": 7879.16,
      "exitPrice": 7887.067314285714,
      "status": "WIN",
      "pnlR": 1.2,
      "dollarPnL": 14.593597547185833,
      "estimatedFee": 14.541636501994635,
      "estimatedSlippage": 5.816654600797855,
      "currentBalance": 4879.126113275797,
      "reason": "TA Entry",
      "regime": "LOW_WINRATE",
      "efficiency": "CHOPPY",
      "effValue": null,
      "riskPercent": 0.25
    },
    {
      "time": "2020-01-09T11:28:00.000Z",
      "type": "SHORT",
      "entryPrice": 7874.49,
      "exitPrice": 7859.767028571428,
      "status": "WIN",
      "pnlR": 1.2000000000000297,
      "dollarPnL": 14.637378339827755,
      "estimatedFee": 7.828711067082123,
      "estimatedSlippage": 3.1314844268328494,
      "currentBalance": 4893.763491615625,
      "reason": "TA Entry",
      "regime": "LOW_WINRATE",
      "efficiency": "CHOPPY",
      "effValue": null,
      "riskPercent": 0.25
    },
    {
      "time": "2020-01-10T09:22:00.000Z",
      "type": "LONG",
      "entryPrice": 7724.54,
      "exitPrice": 7742.198171428572,
      "status": "WIN",
      "pnlR": 1.2000000000000124,
      "dollarPnL": 14.681290474847026,
      "estimatedFee": 6.422307993967927,
      "estimatedSlippage": 2.568923197587171,
      "currentBalance": 4908.444782090472,
      "reason": "TA Entry",
      "regime": "LOW_WINRATE",
      "efficiency": "CHOPPY",
      "effValue": null,
      "riskPercent": 0.25
    },
    {
      "time": "2020-01-10T12:58:00.000Z",
      "type": "LONG",
      "entryPrice": 7886.89,
      "exitPrice": 7872.318571428572,
      "status": "LOSS",
      "pnlR": -1,
      "dollarPnL": -49.084447820904714,
      "estimatedFee": 26.567308673720888,
      "estimatedSlippage": 10.626923469488355,
      "currentBalance": 4859.360334269567,
      "reason": "TA Entry",
      "regime": "HIGH_WINRATE",
      "efficiency": "EXPANSION",
      "effValue": null,
      "riskPercent": 1
    },
    {
      "time": "2020-01-10T14:36:00.000Z",
      "type": "LONG",
      "entryPrice": 7942.41,
      "exitPrice": 7962.922285714286,
      "status": "WIN",
      "pnlR": 1.2000000000000106,
      "dollarPnL": 58.312324011235326,
      "estimatedFee": 22.578682444322443,
      "estimatedSlippage": 9.031472977728978,
      "currentBalance": 4917.672658280802,
      "reason": "TA Entry",
      "regime": "HIGH_WINRATE",
      "efficiency": "EXPANSION",
      "effValue": null,
      "riskPercent": 1
    },
    {
      "time": "2020-01-11T14:09:00.000Z",
      "type": "LONG",
      "entryPrice": 8094,
      "exitPrice": 8105.316857142857,
      "status": "WIN",
      "pnlR": 1.1999999999999806,
      "dollarPnL": 59.01207189936868,
      "estimatedFee": 42.206392103745536,
      "estimatedSlippage": 16.882556841498214,
      "currentBalance": 4976.684730180171,
      "reason": "TA Entry",
      "regime": "HIGH_WINRATE",
      "efficiency": "EXPANSION",
      "effValue": null,
      "riskPercent": 1
    },
    {
      "time": "2020-01-11T15:54:00.000Z",
      "type": "LONG",
      "entryPrice": 8104.99,
      "exitPrice": 8092.244285714286,
      "status": "LOSS",
      "pnlR": -1,
      "dollarPnL": -49.76684730180171,
      "estimatedFee": 31.646700268869267,
      "estimatedSlippage": 12.658680107547708,
      "currentBalance": 4926.917882878369,
      "reason": "TA Entry",
      "regime": "HIGH_WINRATE",
      "efficiency": "EXPANSION",
      "effValue": null,
      "riskPercent": 1
    },
    {
      "time": "2020-01-12T18:08:00.000Z",
      "type": "SHORT",
      "entryPrice": 8093.91,
      "exitPrice": 8107.5075,
      "status": "LOSS",
      "pnlR": -1,
      "dollarPnL": -49.26917882878369,
      "estimatedFee": 29.327471903959175,
      "estimatedSlippage": 11.730988761583669,
      "currentBalance": 4877.648704049585,
      "reason": "TA Entry",
      "regime": "HIGH_WINRATE",
      "efficiency": "EXPANSION",
      "effValue": null,
      "riskPercent": 1
    },
    {
      "time": "2020-01-13T12:14:00.000Z",
      "type": "SHORT",
      "entryPrice": 8065,
      "exitPrice": 8077.596785714286,
      "status": "LOSS",
      "pnlR": -1,
      "dollarPnL": -48.77648704049585,
      "estimatedFee": 31.228789383585873,
      "estimatedSlippage": 12.491515753434351,
      "currentBalance": 4828.872217009089,
      "reason": "TA Entry",
      "regime": "HIGH_WINRATE",
      "efficiency": "EXPANSION",
      "effValue": null,
      "riskPercent": 1
    },
    {
      "time": "2020-01-13T16:52:00.000Z",
      "type": "LONG",
      "entryPrice": 8099.01,
      "exitPrice": 8104.248,
      "status": "WIN",
      "pnlR": 1.1999999999999167,
      "dollarPnL": 57.94646660410504,
      "estimatedFee": 89.59698596627888,
      "estimatedSlippage": 35.83879438651155,
      "currentBalance": 4886.818683613194,
      "reason": "TA Entry",
      "regime": "HIGH_WINRATE",
      "efficiency": "EXPANSION",
      "effValue": null,
      "riskPercent": 1
    },
    {
      "time": "2020-01-13T18:01:00.000Z",
      "type": "SHORT",
      "entryPrice": 8091.56,
      "exitPrice": 8100.928,
      "status": "LOSS",
      "pnlR": -1,
      "dollarPnL": -48.86818683613194,
      "estimatedFee": 42.209635554632115,
      "estimatedSlippage": 16.883854221852847,
      "currentBalance": 4837.950496777062,
      "reason": "TA Entry",
      "regime": "HIGH_WINRATE",
      "efficiency": "EXPANSION",
      "effValue": null,
      "riskPercent": 1
    },
    {
      "time": "2020-01-15T09:33:00.000Z",
      "type": "LONG",
      "entryPrice": 8669.2,
      "exitPrice": 8680.999000000002,
      "status": "WIN",
      "pnlR": 1.200000000000037,
      "dollarPnL": 58.055405961326535,
      "estimatedFee": 42.655642457826445,
      "estimatedSlippage": 17.062256983130577,
      "currentBalance": 4896.005902738389,
      "reason": "TA Entry",
      "regime": "HIGH_WINRATE",
      "efficiency": "EXPANSION",
      "effValue": null,
      "riskPercent": 1
    },
    {
      "time": "2020-01-16T10:23:00.000Z",
      "type": "SHORT",
      "entryPrice": 8624.47,
      "exitPrice": 8652.334,
      "status": "LOSS",
      "pnlR": -1,
      "dollarPnL": -24.480029513691942,
      "estimatedFee": 7.577062881852575,
      "estimatedSlippage": 3.03082515274103,
      "currentBalance": 4871.525873224697,
      "reason": "TA Entry",
      "regime": "NEUTRAL",
      "efficiency": "NEUTRAL",
      "effValue": null,
      "riskPercent": 0.5
    },
    {
      "time": "2020-01-16T10:42:00.000Z",
      "type": "LONG",
      "entryPrice": 8656.31,
      "exitPrice": 8635.915142857142,
      "status": "LOSS",
      "pnlR": -1,
      "dollarPnL": -12.178814683061741,
      "estimatedFee": 5.16912644156744,
      "estimatedSlippage": 2.067650576626976,
      "currentBalance": 4859.347058541635,
      "reason": "TA Entry",
      "regime": "LOW_WINRATE",
      "efficiency": "CHOPPY",
      "effValue": null,
      "riskPercent": 0.25
    },
    {
      "time": "2020-01-16T15:18:00.000Z",
      "type": "LONG",
      "entryPrice": 8695.38,
      "exitPrice": 8720.558571428568,
      "status": "WIN",
      "pnlR": 1.1999999999999653,
      "dollarPnL": 14.578041175624485,
      "estimatedFee": 5.034503567341861,
      "estimatedSlippage": 2.0138014269367446,
      "currentBalance": 4873.925099717259,
      "reason": "TA Entry",
      "regime": "LOW_WINRATE",
      "efficiency": "CHOPPY",
      "effValue": null,
      "riskPercent": 0.25
    },
    {
      "time": "2020-01-17T12:02:00.000Z",
      "type": "SHORT",
      "entryPrice": 8907.77,
      "exitPrice": 8879.17057142857,
      "status": "WIN",
      "pnlR": 1.2000000000000306,
      "dollarPnL": 14.621775299152151,
      "estimatedFee": 4.55419628511892,
      "estimatedSlippage": 1.8216785140475682,
      "currentBalance": 4888.546875016412,
      "reason": "TA Entry",
      "regime": "LOW_WINRATE",
      "efficiency": "CHOPPY",
      "effValue": null,
      "riskPercent": 0.25
    },
    {
      "time": "2020-01-17T16:42:00.000Z",
      "type": "LONG",
      "entryPrice": 8928.98,
      "exitPrice": 8893.022142857142,
      "status": "LOSS",
      "pnlR": -1,
      "dollarPnL": -12.22136718754103,
      "estimatedFee": 3.034784379855249,
      "estimatedSlippage": 1.2139137519420997,
      "currentBalance": 4876.325507828871,
      "reason": "TA Entry",
      "regime": "LOW_WINRATE",
      "efficiency": "CHOPPY",
      "effValue": null,
      "riskPercent": 0.25
    },
    {
      "time": "2020-01-17T17:52:00.000Z",
      "type": "SHORT",
      "entryPrice": 8880.38,
      "exitPrice": 8901.853571428572,
      "status": "LOSS",
      "pnlR": -1,
      "dollarPnL": -12.190813769572179,
      "estimatedFee": 5.041502255138838,
      "estimatedSlippage": 2.0166009020555355,
      "currentBalance": 4864.134694059299,
      "reason": "TA Entry",
      "regime": "LOW_WINRATE",
      "efficiency": "CHOPPY",
      "effValue": null,
      "riskPercent": 0.25
    },
    {
      "time": "2020-01-20T16:02:00.000Z",
      "type": "LONG",
      "entryPrice": 8685.99,
      "exitPrice": 8700.454114285712,
      "status": "WIN",
      "pnlR": 1.1999999999999698,
      "dollarPnL": 14.59240408217753,
      "estimatedFee": 8.76303058936376,
      "estimatedSlippage": 3.5052122357455042,
      "currentBalance": 4878.727098141477,
      "reason": "TA Entry",
      "regime": "LOW_WINRATE",
      "efficiency": "CHOPPY",
      "effValue": null,
      "riskPercent": 0.25
    },
    {
      "time": "2020-01-20T16:03:00.000Z",
      "type": "LONG",
      "entryPrice": 8695.54,
      "exitPrice": 8671.904714285714,
      "status": "LOSS",
      "pnlR": -1,
      "dollarPnL": -12.196817745353693,
      "estimatedFee": 4.487270340604574,
      "estimatedSlippage": 1.7949081362418295,
      "currentBalance": 4866.530280396123,
      "reason": "TA Entry",
      "regime": "LOW_WINRATE",
      "efficiency": "CHOPPY",
      "effValue": null,
      "riskPercent": 0.25
    },
    {
      "time": "2020-01-22T14:00:00.000Z",
      "type": "SHORT",
      "entryPrice": 8641.81,
      "exitPrice": 8649.175714285715,
      "status": "LOSS",
      "pnlR": -1,
      "dollarPnL": -12.166325700990308,
      "estimatedFee": 14.274118032242102,
      "estimatedSlippage": 5.709647212896841,
      "currentBalance": 4854.363954695133,
      "reason": "TA Entry",
      "regime": "LOW_WINRATE",
      "efficiency": "CHOPPY",
      "effValue": null,
      "riskPercent": 0.25
    },
    {
      "time": "2020-01-22T16:05:00.000Z",
      "type": "LONG",
      "entryPrice": 8661.63,
      "exitPrice": 8650.547285714285,
      "status": "LOSS",
      "pnlR": -1,
      "dollarPnL": -12.135909886737831,
      "estimatedFee": 9.484748811738454,
      "estimatedSlippage": 3.793899524695382,
      "currentBalance": 4842.228044808395,
      "reason": "TA Entry",
      "regime": "LOW_WINRATE",
      "efficiency": "CHOPPY",
      "effValue": null,
      "riskPercent": 0.25
    },
    {
      "time": "2020-01-23T08:11:00.000Z",
      "type": "LONG",
      "entryPrice": 8605.51,
      "exitPrice": 8588.856714285715,
      "status": "LOSS",
      "pnlR": -1,
      "dollarPnL": -12.105570112020986,
      "estimatedFee": 6.25549855097602,
      "estimatedSlippage": 2.502199420390408,
      "currentBalance": 4830.1224746963735,
      "reason": "TA Entry",
      "regime": "LOW_WINRATE",
      "efficiency": "CHOPPY",
      "effValue": null,
      "riskPercent": 0.25
    },
    {
      "time": "2020-01-25T11:23:00.000Z",
      "type": "SHORT",
      "entryPrice": 8323.25,
      "exitPrice": 8335.188142857143,
      "status": "LOSS",
      "pnlR": -1,
      "dollarPnL": -12.075306186740933,
      "estimatedFee": 8.41888000683903,
      "estimatedSlippage": 3.367552002735612,
      "currentBalance": 4818.047168509633,
      "reason": "TA Entry",
      "regime": "LOW_WINRATE",
      "efficiency": "CHOPPY",
      "effValue": null,
      "riskPercent": 0.25
    },
    {
      "time": "2020-01-25T17:00:00.000Z",
      "type": "LONG",
      "entryPrice": 8362.39,
      "exitPrice": 8351.764428571429,
      "status": "LOSS",
      "pnlR": -1,
      "dollarPnL": -12.045117921274082,
      "estimatedFee": 9.479581811745602,
      "estimatedSlippage": 3.791832724698241,
      "currentBalance": 4806.0020505883585,
      "reason": "TA Entry",
      "regime": "LOW_WINRATE",
      "efficiency": "CHOPPY",
      "effValue": null,
      "riskPercent": 0.25
    },
    {
      "time": "2020-01-26T20:31:00.000Z",
      "type": "LONG",
      "entryPrice": 8582.73,
      "exitPrice": 8574.595571428572,
      "status": "LOSS",
      "pnlR": -1,
      "dollarPnL": -12.015005126470896,
      "estimatedFee": 12.677171364111835,
      "estimatedSlippage": 5.070868545644734,
      "currentBalance": 4793.987045461888,
      "reason": "TA Entry",
      "regime": "LOW_WINRATE",
      "efficiency": "CHOPPY",
      "effValue": null,
      "riskPercent": 0.25
    },
    {
      "time": "2020-01-28T09:17:00.000Z",
      "type": "SHORT",
      "entryPrice": 8991.55,
      "exitPrice": 9003.864142857143,
      "status": "LOSS",
      "pnlR": -1,
      "dollarPnL": -23.96993522730944,
      "estimatedFee": 17.50238515123988,
      "estimatedSlippage": 7.000954060495952,
      "currentBalance": 4770.0171102345785,
      "reason": "TA Entry",
      "regime": "NEUTRAL",
      "efficiency": "NEUTRAL",
      "effValue": null,
      "riskPercent": 0.5
    },
    {
      "time": "2020-01-28T20:00:00.000Z",
      "type": "LONG",
      "entryPrice": 9051.08,
      "exitPrice": 9102.916914285714,
      "status": "WIN",
      "pnlR": 1.2000000000000084,
      "dollarPnL": 57.24020532281534,
      "estimatedFee": 9.994531594563162,
      "estimatedSlippage": 3.9978126378252647,
      "currentBalance": 4827.257315557394,
      "reason": "TA Entry",
      "regime": "HIGH_WINRATE",
      "efficiency": "EXPANSION",
      "effValue": null,
      "riskPercent": 1
    },
    {
      "time": "2020-01-29T08:43:00.000Z",
      "type": "LONG",
      "entryPrice": 9382.96,
      "exitPrice": 9374.363928571427,
      "status": "LOSS",
      "pnlR": -1,
      "dollarPnL": -48.27257315557394,
      "estimatedFee": 52.69146804787146,
      "estimatedSlippage": 21.076587219148585,
      "currentBalance": 4778.98474240182,
      "reason": "TA Entry",
      "regime": "HIGH_WINRATE",
      "efficiency": "EXPANSION",
      "effValue": null,
      "riskPercent": 1
    },
    {
      "time": "2020-01-29T10:46:00.000Z",
      "type": "LONG",
      "entryPrice": 9376.3,
      "exitPrice": 9388.340714285714,
      "status": "WIN",
      "pnlR": 1.2,
      "dollarPnL": 57.347816908821834,
      "estimatedFee": 44.6576775200231,
      "estimatedSlippage": 17.86307100800924,
      "currentBalance": 4836.332559310642,
      "reason": "TA Entry",
      "regime": "HIGH_WINRATE",
      "efficiency": "EXPANSION",
      "effValue": null,
      "riskPercent": 1
    },
    {
      "time": "2020-01-29T11:20:00.000Z",
      "type": "SHORT",
      "entryPrice": 9285.31,
      "exitPrice": 9243.405999999999,
      "status": "WIN",
      "pnlR": 1.2000000000000104,
      "dollarPnL": 58.03599071172821,
      "estimatedFee": 12.859921843153666,
      "estimatedSlippage": 5.143968737261467,
      "currentBalance": 4894.36855002237,
      "reason": "TA Entry",
      "regime": "HIGH_WINRATE",
      "efficiency": "EXPANSION",
      "effValue": null,
      "riskPercent": 1
    },
    {
      "time": "2020-01-29T16:02:00.000Z",
      "type": "SHORT",
      "entryPrice": 9281.3,
      "exitPrice": 9312.848285714286,
      "status": "LOSS",
      "pnlR": -1,
      "dollarPnL": -24.47184275011185,
      "estimatedFee": 7.199456609896069,
      "estimatedSlippage": 2.879782643958428,
      "currentBalance": 4869.896707272258,
      "reason": "TA Entry",
      "regime": "NEUTRAL",
      "efficiency": "NEUTRAL",
      "effValue": null,
      "riskPercent": 0.5
    }
  ],
  "startTime": "2020-01-01T00:00:00Z",
  "endTime": "2020-02-01T00:00:00Z",
  "displaceTrades": 42,
  "displaceWins": 17,
  "totalProfitR": -4.599999999999904,
  "monthlySnapshots": [
    {
      "month": 1,
      "year": 2020,
      "date": "Tháng 1/2020",
      "balance": 4869.896707272258,
      "monthlyProfit": -130.10329272774035,
      "monthlyProfitR": -4.599999999999904,
      "totalProfitR": -4.599999999999904,
      "winRate": "40.5",
      "trades": 42,
      "wins": 17,
      "losses": 25,
      "longTrades": 24,
      "longWins": 11,
      "shortTrades": 18,
      "shortWins": 6,
      "continuationTrades": 17,
      "continuationWins": 8,
      "continuationPnLR": 0.6000000000000678,
      "whaleTrades": 25,
      "whaleWins": 9,
      "whalePnLR": -5.199999999999971
    }
  ],
  "marketRegime": {
    "tqs5m": 100,
    "tqs1m": 100,
    "totalScore": 25,
    "regime": "LOW_WINRATE",
    "riskPercent": 0.25
  },
  "continuationTrades": 17,
  "continuationWins": 8,
  "continuationPnLR": 0.6000000000000678,
  "efficiencyStats": {
    "CHOPPY": {
      "trades": 17,
      "wins": 7,
      "pnlR": -1.6000000000000334
    },
    "NEUTRAL": {
      "trades": 4,
      "wins": 1,
      "pnlR": -1.7999999999999459
    },
    "EXPANSION": {
      "trades": 21,
      "wins": 9,
      "pnlR": -1.1999999999999234
    }
  },
  "regimeStats": {
    "TREND_EXPANSION": {
      "trades": 0,
      "wins": 0,
      "pnlR": 0
    },
    "NEUTRAL": {
      "trades": 4,
      "wins": 1,
      "pnlR": -1.7999999999999459
    },
    "COMPRESSION": {
      "trades": 0,
      "wins": 0,
      "pnlR": 0
    },
    "CHOPPY": {
      "trades": 0,
      "wins": 0,
      "pnlR": 0
    }
  }
}